byts/__init__.py
byts/vec.py
byts-0.0.1.dist-info/METADATA
byts-0.0.1.dist-info/WHEEL
byts-0.0.1.dist-info/top_level.txt
byts-0.0.1.dist-info/RECORD
